README.rst
setup.cfg
setup.py
pysplunk/__init__.py
pysplunk/aerospikeclient.py
pysplunk/settings.py
pysplunk/splunk.py
pysplunk.egg-info/PKG-INFO
pysplunk.egg-info/SOURCES.txt
pysplunk.egg-info/dependency_links.txt
pysplunk.egg-info/requires.txt
pysplunk.egg-info/top_level.txt