Metadata-Version: 1.1
Name: pysplunk
Version: 1.0.0
Summary: Simple splunk log python package.
Home-page: http://www.lojaintegrada.com.br
Author: Loja Integrada
Author-email: suporte@lojaintegrada.com.br
License: MIT
Platform: UNKNOWN
Classifier: Development Status :: 3 - Alpha
Classifier: Environment :: Web Environment
Classifier: Intended Audience :: Developers
Classifier: License :: OSI Approved :: MIT License
Classifier: Operating System :: OS Independent
Classifier: Programming Language :: Python
Classifier: Programming Language :: Python :: 3.4
Classifier: Programming Language :: Python :: 3.5
Classifier: Topic :: Software Development :: Libraries :: Python Modules
Classifier: Topic :: Internet
